llm_prompt_optimizer-0.3.0.dist-info/licenses/LICENSE
prompt_optimizer/__init__.py
prompt_optimizer/types.py
prompt_optimizer/analytics/__init__.py
prompt_optimizer/analytics/cost_tracker.py
prompt_optimizer/analytics/performance.py
prompt_optimizer/analytics/quality_scorer.py
prompt_optimizer/analytics/reports.py
prompt_optimizer/analytics/advanced/__init__.py
prompt_optimizer/analytics/advanced/predictive_analytics.py
prompt_optimizer/api/__init__.py
prompt_optimizer/api/server.py
prompt_optimizer/cli/__init__.py
prompt_optimizer/cli/main.py
prompt_optimizer/core/__init__.py
prompt_optimizer/core/experiment.py
prompt_optimizer/core/metrics.py
prompt_optimizer/core/optimizer.py
prompt_optimizer/core/prompt.py
prompt_optimizer/integrations/streamlit_app.py
prompt_optimizer/monitoring/__init__.py
prompt_optimizer/monitoring/real_time_dashboard.py
prompt_optimizer/optimization/__init__.py
prompt_optimizer/optimization/genetic.py
prompt_optimizer/optimization/rlhf.py
prompt_optimizer/optimization/suggestions.py
prompt_optimizer/optimization/templates.py
prompt_optimizer/providers/__init__.py
prompt_optimizer/providers/anthropic.py
prompt_optimizer/providers/base.py
prompt_optimizer/providers/google.py
prompt_optimizer/providers/huggingface.py
prompt_optimizer/providers/openai.py
prompt_optimizer/security/__init__.py
prompt_optimizer/security/audit_logger.py
prompt_optimizer/security/bias_detector.py
prompt_optimizer/security/compliance_checker.py
prompt_optimizer/security/content_moderator.py
prompt_optimizer/security/injection_detector.py
prompt_optimizer/storage/__init__.py
prompt_optimizer/storage/cache.py
prompt_optimizer/storage/database.py
prompt_optimizer/storage/models.py
prompt_optimizer/testing/__init__.py
prompt_optimizer/testing/ab_test.py
prompt_optimizer/testing/randomization.py
prompt_optimizer/testing/significance.py
prompt_optimizer/testing/statistical.py
prompt_optimizer/visualization/__init__.py
prompt_optimizer/visualization/charts.py
prompt_optimizer/visualization/dashboard.py
llm_prompt_optimizer-0.3.0.dist-info/METADATA
llm_prompt_optimizer-0.3.0.dist-info/WHEEL
llm_prompt_optimizer-0.3.0.dist-info/entry_points.txt
llm_prompt_optimizer-0.3.0.dist-info/top_level.txt
llm_prompt_optimizer-0.3.0.dist-info/RECORD
