Metadata-Version: 2.4
Name: llm-prompt-optimizer
Version: 0.3.0
Summary: A comprehensive framework for systematic A/B testing, optimization, performance analytics, security, and monitoring of LLM prompts across multiple providers with enterprise-ready API
Home-page: https://github.com/Sherin-SEF-AI/prompt-optimizer.git
Author: Sherin Joseph Roy
Author-email: Sherin Joseph Roy <sherin.joseph2217@gmail.com>
Maintainer-email: Sherin Joseph Roy <sherin.joseph2217@gmail.com>
License: MIT
Project-URL: Homepage, https://github.com/Sherin-SEF-AI/prompt-optimizer.git
Project-URL: Documentation, https://github.com/Sherin-SEF-AI/prompt-optimizer#readme
Project-URL: Repository, https://github.com/Sherin-SEF-AI/prompt-optimizer.git
Project-URL: Bug Tracker, https://github.com/Sherin-SEF-AI/prompt-optimizer/issues
Project-URL: Source Code, https://github.com/Sherin-SEF-AI/prompt-optimizer.git
Project-URL: LinkedIn, https://www.linkedin.com/in/sherin-roy-deepmost/
Keywords: llm,prompt,optimization,a/b testing,machine learning,ai
Classifier: Development Status :: 3 - Alpha
Classifier: Intended Audience :: Developers
Classifier: Intended Audience :: Science/Research
Classifier: License :: OSI Approved :: MIT License
Classifier: Operating System :: OS Independent
Classifier: Programming Language :: Python :: 3
Classifier: Programming Language :: Python :: 3.8
Classifier: Programming Language :: Python :: 3.9
Classifier: Programming Language :: Python :: 3.10
Classifier: Programming Language :: Python :: 3.11
Classifier: Programming Language :: Python :: 3.12
Classifier: Topic :: Scientific/Engineering :: Artificial Intelligence
Classifier: Topic :: Software Development :: Libraries :: Python Modules
Classifier: Topic :: Software Development :: Testing
Requires-Python: >=3.8
License-File: LICENSE
Requires-Dist: pydantic>=2.0.0
Requires-Dist: typing-extensions>=4.0.0
Requires-Dist: sqlalchemy>=2.0.0
Requires-Dist: alembic>=1.11.0
Requires-Dist: psycopg2-binary>=2.9.0
Requires-Dist: redis>=4.5.0
Requires-Dist: cachetools>=5.3.0
Requires-Dist: fastapi>=0.100.0
Requires-Dist: uvicorn[standard]>=0.22.0
Requires-Dist: requests>=2.31.0
Requires-Dist: httpx>=0.24.0
Requires-Dist: click>=8.1.0
Requires-Dist: rich>=13.0.0
Requires-Dist: numpy>=1.24.0
Requires-Dist: pandas>=2.0.0
Requires-Dist: scipy>=1.10.0
Requires-Dist: scikit-learn>=1.3.0
Requires-Dist: matplotlib>=3.7.0
Requires-Dist: seaborn>=0.12.0
Requires-Dist: plotly>=5.15.0
Requires-Dist: dash>=2.11.0
Requires-Dist: streamlit>=1.28.0
Requires-Dist: openai>=1.0.0
Requires-Dist: anthropic>=0.7.0
Requires-Dist: google-generativeai>=0.3.0
Requires-Dist: transformers>=4.30.0
Requires-Dist: torch>=2.0.0
Requires-Dist: tiktoken>=0.4.0
Requires-Dist: asyncio-mqtt>=0.13.0
Requires-Dist: websockets>=11.0.0
Provides-Extra: dev
Requires-Dist: pytest>=7.4.0; extra == "dev"
Requires-Dist: pytest-asyncio>=0.21.0; extra == "dev"
Requires-Dist: pytest-cov>=4.1.0; extra == "dev"
Requires-Dist: black>=23.0.0; extra == "dev"
Requires-Dist: flake8>=6.0.0; extra == "dev"
Requires-Dist: mypy>=1.4.0; extra == "dev"
Requires-Dist: pre-commit>=3.3.0; extra == "dev"
Provides-Extra: docs
Requires-Dist: sphinx>=7.0.0; extra == "docs"
Requires-Dist: sphinx-rtd-theme>=1.2.0; extra == "docs"
Dynamic: author
Dynamic: home-page
Dynamic: license-file
Dynamic: requires-python
